LICENSE
README.md
pyproject.toml
setup.cfg
setup.py
cassava/__init__.py
cassava/augment.py
cassava/config.py
cassava/dataset.py
cassava/loss.py
cassava/model.py
cassava/pretrained.py
cassava/train.py
cassava/utils.py
cassava/valid.py
cassava_classifier.egg-info/PKG-INFO
cassava_classifier.egg-info/SOURCES.txt
cassava_classifier.egg-info/dependency_links.txt
cassava_classifier.egg-info/requires.txt
cassava_classifier.egg-info/top_level.txt